{
  "cancelados":[
    {"id-clientes-ja-cancelaram-compr":"24259"},
    {"id-clientes-ja-cancelaram-compr":"20599"},
    {"id-clientes-ja-cancelaram-compr":"21228"},
    {"id-clientes-ja-cancelaram-compr":"21158"},
    {"id-clientes-ja-cancelaram-compr":"21015"},
    {"id-clientes-ja-cancelaram-compr":"20576"},
    {"id-clientes-ja-cancelaram-compr":"22063"},
    {"id-clientes-ja-cancelaram-compr":"22071"},
    {"id-clientes-ja-cancelaram-compr":"20870"},
    {"id-clientes-ja-cancelaram-compr":"20956"},
    {"id-clientes-ja-cancelaram-compr":"21018"},
    {"id-clientes-ja-cancelaram-compr":"21708"},
    {"id-clientes-ja-cancelaram-compr":"22213"},
    {"id-clientes-ja-cancelaram-compr":"22815"},
    {"id-clientes-ja-cancelaram-compr":"21970"},
    {"id-clientes-ja-cancelaram-compr":"21479"},
    {"id-clientes-ja-cancelaram-compr":"21887"},
    {"id-clientes-ja-cancelaram-compr":"20563"},
    {"id-clientes-ja-cancelaram-compr":"22104"},
    {"id-clientes-ja-cancelaram-compr":"22494"},
    {"id-clientes-ja-cancelaram-compr":"20234"},
    {"id-clientes-ja-cancelaram-compr":"20942"},
    {"id-clientes-ja-cancelaram-compr":"20285"},
    {"id-clientes-ja-cancelaram-compr":"21141"},
    {"id-clientes-ja-cancelaram-compr":"22112"},
    {"id-clientes-ja-cancelaram-compr":"20733"},
    {"id-clientes-ja-cancelaram-compr":"21936"},
    {"id-clientes-ja-cancelaram-compr":"20501"},
    {"id-clientes-ja-cancelaram-compr":"22063"},
    {"id-clientes-ja-cancelaram-compr":"21143"},
    {"id-clientes-ja-cancelaram-compr":"20597"},
    {"id-clientes-ja-cancelaram-compr":"22696"},
    {"id-clientes-ja-cancelaram-compr":"21270"},
    {"id-clientes-ja-cancelaram-compr":"21943"},
    {"id-clientes-ja-cancelaram-compr":"22214"},
    {"id-clientes-ja-cancelaram-compr":"21825"},
    {"id-clientes-ja-cancelaram-compr":"22727"},
    {"id-clientes-ja-cancelaram-compr":"22539"},
    {"id-clientes-ja-cancelaram-compr":"20735"},
    {"id-clientes-ja-cancelaram-compr":"21940"},
    {"id-clientes-ja-cancelaram-compr":"21933"},
    {"id-clientes-ja-cancelaram-compr":"21569"},
    {"id-clientes-ja-cancelaram-compr":"20456"},
    {"id-clientes-ja-cancelaram-compr":"20304"},
    {"id-clientes-ja-cancelaram-compr":"22901"},
    {"id-clientes-ja-cancelaram-compr":"21199"},
    {"id-clientes-ja-cancelaram-compr":"20215"},
    {"id-clientes-ja-cancelaram-compr":"22229"},
    {"id-clientes-ja-cancelaram-compr":"20518"},
    {"id-clientes-ja-cancelaram-compr":"21262"},
    {"id-clientes-ja-cancelaram-compr":"20972"},
    {"id-clientes-ja-cancelaram-compr":"22598"},
    {"id-clientes-ja-cancelaram-compr":"21888"},
    {"id-clientes-ja-cancelaram-compr":"22410"},
    {"id-clientes-ja-cancelaram-compr":"20967"},
    {"id-clientes-ja-cancelaram-compr":"20522"},
    {"id-clientes-ja-cancelaram-compr":"22510"},
    {"id-clientes-ja-cancelaram-compr":"22417"},
    {"id-clientes-ja-cancelaram-compr":"21992"},
    {"id-clientes-ja-cancelaram-compr":"22584"},
    {"id-clientes-ja-cancelaram-compr":"22372"},
    {"id-clientes-ja-cancelaram-compr":"20804"},
    {"id-clientes-ja-cancelaram-compr":"21035"},
    {"id-clientes-ja-cancelaram-compr":"22249"},
    {"id-clientes-ja-cancelaram-compr":"21070"},
    {"id-clientes-ja-cancelaram-compr":"22397"},
    {"id-clientes-ja-cancelaram-compr":"21613"},
    {"id-clientes-ja-cancelaram-compr":"20492"},
    {"id-clientes-ja-cancelaram-compr":"22019"},
    {"id-clientes-ja-cancelaram-compr":"20192"},
    {"id-clientes-ja-cancelaram-compr":"22127"},
    {"id-clientes-ja-cancelaram-compr":"21468"},
    {"id-clientes-ja-cancelaram-compr":"20277"},
    {"id-clientes-ja-cancelaram-compr":"22055"},
    {"id-clientes-ja-cancelaram-compr":"21216"},
    {"id-clientes-ja-cancelaram-compr":"21527"},
    {"id-clientes-ja-cancelaram-compr":"21834"},
    {"id-clientes-ja-cancelaram-compr":"20148"},
    {"id-clientes-ja-cancelaram-compr":"22557"},
    {"id-clientes-ja-cancelaram-compr":"21036"},
    {"id-clientes-ja-cancelaram-compr":"20326"},
    {"id-clientes-ja-cancelaram-compr":"21017"},
    {"id-clientes-ja-cancelaram-compr":"20974"},
    {"id-clientes-ja-cancelaram-compr":"20172"},
    {"id-clientes-ja-cancelaram-compr":"21302"},
    {"id-clientes-ja-cancelaram-compr":"20809"},
    {"id-clientes-ja-cancelaram-compr":"21348"},
    {"id-clientes-ja-cancelaram-compr":"21987"},
    {"id-clientes-ja-cancelaram-compr":"22753"},
    {"id-clientes-ja-cancelaram-compr":"20262"},
    {"id-clientes-ja-cancelaram-compr":"21213"},
    {"id-clientes-ja-cancelaram-compr":"20720"},
    {"id-clientes-ja-cancelaram-compr":"20370"},
    {"id-clientes-ja-cancelaram-compr":"22200"},
    {"id-clientes-ja-cancelaram-compr":"22741"},
    {"id-clientes-ja-cancelaram-compr":"21625"},
    {"id-clientes-ja-cancelaram-compr":"21035"},
    {"id-clientes-ja-cancelaram-compr":"22228"},
    {"id-clientes-ja-cancelaram-compr":"21425"},
    {"id-clientes-ja-cancelaram-compr":"21388"},
    {"id-clientes-ja-cancelaram-compr":"21760"},
    {"id-clientes-ja-cancelaram-compr":"20883"},
    {"id-clientes-ja-cancelaram-compr":"22140"},
    {"id-clientes-ja-cancelaram-compr":"22001"},
    {"id-clientes-ja-cancelaram-compr":"21270"},
    {"id-clientes-ja-cancelaram-compr":"20348"},
    {"id-clientes-ja-cancelaram-compr":"22280"},
    {"id-clientes-ja-cancelaram-compr":"21107"},
    {"id-clientes-ja-cancelaram-compr":"20700"},
    {"id-clientes-ja-cancelaram-compr":"22175"},
    {"id-clientes-ja-cancelaram-compr":"21719"},
    {"id-clientes-ja-cancelaram-compr":"21547"},
    {"id-clientes-ja-cancelaram-compr":"22001"},
    {"id-clientes-ja-cancelaram-compr":"21609"},
    {"id-clientes-ja-cancelaram-compr":"21858"},
    {"id-clientes-ja-cancelaram-compr":"21726"},
    {"id-clientes-ja-cancelaram-compr":"22936"},
    {"id-clientes-ja-cancelaram-compr":"20308"},
    {"id-clientes-ja-cancelaram-compr":"21238"},
    {"id-clientes-ja-cancelaram-compr":"22006"},
    {"id-clientes-ja-cancelaram-compr":"22674"},
    {"id-clientes-ja-cancelaram-compr":"21525"},
    {"id-clientes-ja-cancelaram-compr":"22070"},
    {"id-clientes-ja-cancelaram-compr":"21070"},
    {"id-clientes-ja-cancelaram-compr":"21974"},
    {"id-clientes-ja-cancelaram-compr":"20511"},
    {"id-clientes-ja-cancelaram-compr":"22358"},
    {"id-clientes-ja-cancelaram-compr":"20199"},
    {"id-clientes-ja-cancelaram-compr":"22712"},
    {"id-clientes-ja-cancelaram-compr":"22222"},
    {"id-clientes-ja-cancelaram-compr":"22806"},
    {"id-clientes-ja-cancelaram-compr":"20214"},
    {"id-clientes-ja-cancelaram-compr":"22413"},
    {"id-clientes-ja-cancelaram-compr":"22872"},
    {"id-clientes-ja-cancelaram-compr":"21793"},
    {"id-clientes-ja-cancelaram-compr":"20845"},
    {"id-clientes-ja-cancelaram-compr":"21385"},
    {"id-clientes-ja-cancelaram-compr":"20308"},
    {"id-clientes-ja-cancelaram-compr":"20248"},
    {"id-clientes-ja-cancelaram-compr":"22177"},
    {"id-clientes-ja-cancelaram-compr":"22147"},
    {"id-clientes-ja-cancelaram-compr":"20569"},
    {"id-clientes-ja-cancelaram-compr":"21261"},
    {"id-clientes-ja-cancelaram-compr":"22648"},
    {"id-clientes-ja-cancelaram-compr":"21014"},
    {"id-clientes-ja-cancelaram-compr":"21331"},
    {"id-clientes-ja-cancelaram-compr":"20734"},
    {"id-clientes-ja-cancelaram-compr":"20413"},
    {"id-clientes-ja-cancelaram-compr":"21172"},
    {"id-clientes-ja-cancelaram-compr":"22773"},
    {"id-clientes-ja-cancelaram-compr":"21295"},
    {"id-clientes-ja-cancelaram-compr":"21476"},
    {"id-clientes-ja-cancelaram-compr":"22608"},
    {"id-clientes-ja-cancelaram-compr":"22340"},
    {"id-clientes-ja-cancelaram-compr":"21892"},
    {"id-clientes-ja-cancelaram-compr":"22230"},
    {"id-clientes-ja-cancelaram-compr":"20287"},
    {"id-clientes-ja-cancelaram-compr":"22173"},
    {"id-clientes-ja-cancelaram-compr":"21962"}
  ]
}
